fivecentplots/__init__.py
fivecentplots/colors.py
fivecentplots/fcp.py
fivecentplots/py.typed
fivecentplots/utilities.py
fivecentplots/version.txt
fivecentplots/data/__init__.py
fivecentplots/data/bar.py
fivecentplots/data/box.py
fivecentplots/data/contour.py
fivecentplots/data/data.py
fivecentplots/data/gantt.py
fivecentplots/data/heatmap.py
fivecentplots/data/hist.py
fivecentplots/data/imshow.py
fivecentplots/data/nq.py
fivecentplots/data/pie.py
fivecentplots/data/template.py
fivecentplots/data/xy.py
fivecentplots/engines/__init__.py
fivecentplots/engines/bokeh.py
fivecentplots/engines/layout.py
fivecentplots/engines/mpl.py
fivecentplots/engines/new_engine_template.py
fivecentplots/engines/plotly.py
fivecentplots/kwargs/__init__.py
fivecentplots/kwargs/keywords.py
fivecentplots/kwargs/kwargs_all.txt
fivecentplots/test_data/RAW.png
fivecentplots/test_data/fake_data.csv
fivecentplots/test_data/fake_data_bar.csv
fivecentplots/test_data/fake_data_box.csv
fivecentplots/test_data/fake_data_box_small.csv
fivecentplots/test_data/fake_data_contour.csv
fivecentplots/test_data/fake_data_gantt.csv
fivecentplots/test_data/fake_data_gantt_milestone.csv
fivecentplots/test_data/fake_data_heatmap.csv
fivecentplots/test_data/fake_data_interval.csv
fivecentplots/test_data/fake_ts.csv
fivecentplots/test_data/hist_patch.png
fivecentplots/test_data/imshow_cat_pirate.png
fivecentplots/test_data/imshow_color_bars.png
fivecentplots/test_data/imshow_color_planes.png
fivecentplots/test_data/real_data_bar.csv
fivecentplots/themes/_test.py
fivecentplots/themes/gray.py
fivecentplots/themes/gray_bokeh.py
fivecentplots/themes/gray_original.py
fivecentplots/themes/gray_plotly.py
fivecentplots/themes/mpl.py
fivecentplots/themes/science.py
fivecentplots/themes/white.py
fivecentplots-0.6.0.dist-info/METADATA
fivecentplots-0.6.0.dist-info/WHEEL
fivecentplots-0.6.0.dist-info/top_level.txt
fivecentplots-0.6.0.dist-info/RECORD
